{
  "url": "https://exrx.net/Plyometrics/AlternateBoundDoubleArm",
  "name": "Alternate Bound (with double arm action)",
  "classification": {
    "utility": "Plyometric",
    "mechanics": "Compound",
    "force": "Push",
    "intensity": "Medium",
    "function": "Leg Ext (Horizontal)",
    "bearing": "",
    "impact": "",
    "exercise_dictionary_id": 0
  },
  "muscles": {
    "target": null,
    "synergists": null,
    "stabilizers": null,
    "dynamic_stabilizers": null,
    "antagonist_stabilizers": null,
    "rom_criteria": null,
    "dynamic_articulation": [
      "quadriceps",
      "serratus anterior",
      "pectoralis minor",
      "deltoid anterior",
      "pectoralis clavicular",
      "levator scapulae",
      "hamstrings",
      "gracilis",
      "popliteus",
      "deltoid posterior",
      "triceps brachii",
      "trapezius lower",
      "soleus",
      "teres major",
      "gastrocnemius",
      "deltoid lateral",
      "pectoralis sternal",
      "latissimus dorsi",
      "rhomboids",
      "gluteus maximus",
      "tensor fasciae latae",
      "sartorius",
      "tibialis anterior",
      "biceps brachii",
      "trapezius middle",
      "adductors",
      "iliopsoas",
      "pectineus"
    ],
    "static_articulation": [
      "gluteus minimus",
      "sartorius",
      "quadriceps",
      "sternocleidomastoid",
      "levator scapulae",
      "# rotation 1",
      "tensor fasciae latae",
      "splenius",
      "erector spinae",
      "gluteus medius"
    ],
    "exercise_dictionary_id": 0
  },
  "articulation": {
    "dynamic": {
      "ankle": null,
      "elbow": null,
      "finger": null,
      "foot": null,
      "forearms": null,
      "hip": null,
      "scapula": null,
      "clavicle": null,
      "shoulder": null,
      "shoulder_girdle": null,
      "spine": null,
      "thumb": null,
      "wrist": null,
      "knee": null,
      "articulation_id": 0
    },
    "static": {
      "ankle": null,
      "elbow": null,
      "finger": null,
      "foot": null,
      "forearms": null,
      "hip": null,
      "scapula": null,
      "clavicle": null,
      "shoulder": null,
      "shoulder_girdle": null,
      "spine": null,
      "thumb": null,
      "wrist": null,
      "knee": null,
      "articulation_id": 0
    },
    "exercise_dictionary_id": 0
  }
}