{
  "url": "http://exrx.net/Plyometrics/SeatedBoxJump",
  "name": "Seated Box Jump",
  "classification": {
    "utility": "Plyometric",
    "mechanics": "Compound",
    "force": "Push",
    "intensity": "Medium High",
    "function": "Leg Ext (Vertical)",
    "bearing": "",
    "impact": "",
    "exercise_dictionary_id": 0
  },
  "muscles": {
    "target": null,
    "synergists": null,
    "stabilizers": null,
    "dynamic_stabilizers": null,
    "antagonist_stabilizers": null,
    "rom_criteria": null,
    "dynamic_articulation": [
      "sartorius",
      "pectineus",
      "trapezius upper",
      "trapezius lower",
      "rectus abdominis",
      "adductors",
      "iliopsoas",
      "tensor fasciae latae",
      "quadriceps",
      "gastrocnemius",
      "deltoid lateral",
      "pectoralis clavicular",
      "biceps brachii",
      "trapezius middle",
      "gluteus maximus",
      "hamstrings",
      "soleus",
      "deltoid anterior",
      "supraspinatus",
      "levator scapulae",
      "serratus anterior",
      "obliques"
    ],
    "static_articulation": [
      "erector spinae",
      "quadratus lumborum",
      "trapezius lower"
    ],
    "exercise_dictionary_id": 0
  },
  "articulation": {
    "dynamic": {
      "ankle": null,
      "elbow": null,
      "finger": null,
      "foot": null,
      "forearms": null,
      "hip": null,
      "scapula": null,
      "clavicle": null,
      "shoulder": null,
      "shoulder_girdle": null,
      "spine": null,
      "thumb": null,
      "wrist": null,
      "knee": null,
      "articulation_id": 0
    },
    "static": {
      "ankle": null,
      "elbow": null,
      "finger": null,
      "foot": null,
      "forearms": null,
      "hip": null,
      "scapula": null,
      "clavicle": null,
      "shoulder": null,
      "shoulder_girdle": null,
      "spine": null,
      "thumb": null,
      "wrist": null,
      "knee": null,
      "articulation_id": 0
    },
    "exercise_dictionary_id": 0
  }
}