{
  "url": "https://exrx.net/WeightExercises/DeltoidLateral/BBUprightRow",
  "name": "Barbell Upright Row",
  "classification": {
    "utility": "Basic",
    "mechanics": "Compound",
    "force": "Pull",
    "intensity": "",
    "function": "",
    "bearing": "",
    "impact": "",
    "exercise_type_id": 0
  },
  "muscles": {
    "target": [
      "Deltoid, Lateral"
    ],
    "synergists": [
      "Deltoid, Anterior",
      "Supraspinatus",
      "Brachialis",
      "Brachioradialis",
      "Biceps Brachii",
      "Trapezius, Middle",
      "Trapezius, Lower",
      "Serratus Anterior, Inferior Digitations",
      "Infraspinatus",
      "Teres Minor"
    ],
    "stabilizers": [
      "Trapezius, Upper",
      "Levator Scapulae"
    ],
    "dynamic_stabilizers": null,
    "antagonist_stabilizers": null,
    "rom_criteria": null,
    "exercise_type_id": 0
  },
  "articulation": {
    "dynamic": {
      "ankle": null,
      "elbow": null,
      "finger": null,
      "foot": null,
      "forearms": null,
      "hip": null,
      "scapula": null,
      "clavicle": null,
      "shoulder": null,
      "shoulder_girdle": null,
      "spine": null,
      "thumb": null,
      "wrist": null,
      "knee": null,
      "articulation_id": 0
    },
    "static": {
      "ankle": null,
      "elbow": null,
      "finger": null,
      "foot": null,
      "forearms": null,
      "hip": null,
      "scapula": null,
      "clavicle": null,
      "shoulder": null,
      "shoulder_girdle": null,
      "spine": null,
      "thumb": null,
      "wrist": null,
      "knee": null,
      "articulation_id": 0
    },
    "exercise_type_id": 0
  }
}