{
  "URL": "https://exrx.net/WeightExercises/Triceps/CBInclinePushdown",
  "Name": "Cable Incline Pushdown",
  "Classification": {
    "Utility": "Auxiliary",
    "Mechanics": "Isolated",
    "Force": "Push",
    "Intensity": "",
    "Function": "",
    "Bearing": "",
    "Impact": ""
  },
  "Muscles": {
    "Target": [
      "Triceps Brachii"
    ],
    "Synergists": null,
    "Stabilizers": [
      "Latissimus Dorsi",
      "Teres Major",
      "Deltoid, Posterior",
      "Pectoralis Major, Sternal",
      "Pectoralis Minor",
      "Trapezius, Lower",
      "Wrist Flexors"
    ],
    "DynamicStabilizers": null,
    "AntagonistStabilizers": null,
    "ROMCriteria": null
  },
  "Articulation": {
    "Dynamic": null,
    "Static": null
  },
  "CrawledAt": "2018-11-25T15:55:21.488791-08:00"
}