{
  "URL": "https://exrx.net/WeightExercises/BackGeneral/CBLyingRow",
  "Name": "Cable Lying Row",
  "Classification": {
    "Utility": "Basic or Auxiliary",
    "Mechanics": "Compound",
    "Force": "Pull",
    "Intensity": "",
    "Function": "",
    "Bearing": "",
    "Impact": ""
  },
  "Muscles": {
    "Target": null,
    "Synergists": [
      "Trapezius, Middle",
      "Trapezius, Lower",
      "Rhomboids",
      "Latissimus Dorsi",
      "Teres Major",
      "Deltoid, Posterior",
      "Infraspinatus",
      "Teres Minor",
      "Brachialis",
      "Brachioradialis",
      "Pectoralis Major, Sternal"
    ],
    "Stabilizers": null,
    "DynamicStabilizers": [
      "Biceps Brachii",
      "Triceps, Long Head"
    ],
    "AntagonistStabilizers": null,
    "ROMCriteria": null
  },
  "Articulation": {
    "Dynamic": null,
    "Static": null
  },
  "CrawledAt": "2018-11-25T15:06:53.468881-08:00"
}