{
  "URL": "https://exrx.net/WeightExercises/Brachialis/DBProneInclineCurl",
  "Name": "Dumbbell Prone Incline Curl",
  "Classification": {
    "Utility": "Auxiliary",
    "Mechanics": "Isolated",
    "Force": "Pull",
    "Intensity": "",
    "Function": "",
    "Bearing": "",
    "Impact": ""
  },
  "Muscles": {
    "Target": [
      "Brachialis"
    ],
    "Synergists": [
      "Biceps Brachii",
      "Brachioradialis"
    ],
    "Stabilizers": [
      "Wrist Flexors",
      "Trapezius, Middle",
      "Rhomboids"
    ],
    "DynamicStabilizers": null,
    "AntagonistStabilizers": null,
    "ROMCriteria": null
  },
  "Articulation": {
    "Dynamic": null,
    "Static": null
  },
  "CrawledAt": "2018-11-26T12:39:53.959736-08:00"
}