{
  "URL": "https://exrx.net/WeightExercises/LatissimusDorsi/LVPullover",
  "Name": "Lever Pullover",
  "Classification": {
    "Utility": "Auxiliary",
    "Mechanics": "Isolated",
    "Force": "Pull",
    "Intensity": "",
    "Function": "",
    "Bearing": "",
    "Impact": ""
  },
  "Muscles": {
    "Target": [
      "Latissimus Dorsi"
    ],
    "Synergists": [
      "Pectoralis Major, Sternal",
      "Pectoralis Minor",
      "Triceps, Long Head",
      "Teres Major",
      "Deltoid, Posterior",
      "Rhomboids",
      "Levator Scapulae"
    ],
    "Stabilizers": [
      "Trapezius, Lower"
    ],
    "DynamicStabilizers": null,
    "AntagonistStabilizers": null,
    "ROMCriteria": null
  },
  "Articulation": {
    "Dynamic": {
      "Ankle": null,
      "Elbow": null,
      "Finger": null,
      "Foot": null,
      "Forearms": null,
      "Hip": null,
      "Scapula": null,
      "Clavicle": null,
      "Shoulder": null,
      "ShoulderGirdle": null,
      "Spine": null,
      "Thumb": null,
      "Wrist": null,
      "Knee": null
    },
    "Static": {
      "Ankle": null,
      "Elbow": null,
      "Finger": null,
      "Foot": null,
      "Forearms": null,
      "Hip": null,
      "Scapula": null,
      "Clavicle": null,
      "Shoulder": null,
      "ShoulderGirdle": null,
      "Spine": null,
      "Thumb": null,
      "Wrist": null,
      "Knee": null
    }
  },
  "CrawledAt": "2018-11-26T21:06:24.647256-08:00"
}