{
  "URL": "https://exrx.net/WeightExercises/BackGeneral/STBentKneeInvertedRow",
  "Name": "Suspended Bent-knee Inverted Row",
  "Classification": {
    "Utility": "Basic or Auxiliary",
    "Mechanics": "Compound",
    "Force": "Pull",
    "Intensity": "",
    "Function": "",
    "Bearing": "",
    "Impact": ""
  },
  "Muscles": {
    "Target": null,
    "Synergists": [
      "Trapezius, Middle",
      "Trapezius, Lower",
      "Rhomboids",
      "Latissimus Dorsi",
      "Teres Major",
      "Deltoid, Posterior",
      "Infraspinatus",
      "Teres Minor",
      "Brachialis",
      "Brachioradialis",
      "Pectoralis Major, Sternal "
    ],
    "Stabilizers": [
      "Erector Spinae",
      "Gluteus Maximus"
    ],
    "DynamicStabilizers": [
      "Biceps Brachii",
      "Triceps, Long Head "
    ],
    "AntagonistStabilizers": [
      "Rectus Abdominis",
      "Obliques"
    ],
    "ROMCriteria": null
  },
  "Articulation": {
    "Dynamic": null,
    "Static": null
  },
  "CrawledAt": "2018-11-25T15:06:53.471948-08:00"
}